ansatzes/__init__.py
ansatzes/strongly_entangling.py
core/__init__.py
core/base_model.py
feature_maps/__init__.py
feature_maps/zz_map.py
models/__init__.py
models/classifier.py
utils/__init__.py
utils/metrics.py
utils/visualization.py
quantummlsystem-0.1.3.dist-info/METADATA
quantummlsystem-0.1.3.dist-info/WHEEL
quantummlsystem-0.1.3.dist-info/top_level.txt
quantummlsystem-0.1.3.dist-info/RECORD
